commonroad_path_toolkit-0.0.1.dist-info/METADATA
commonroad_path_toolkit-0.0.1.dist-info/WHEEL
commonroad_path_toolkit-0.0.1.dist-info/licenses/LICENSE
commonroad_path_toolkit.libs/libgfortran-91cc3cb1.so.3
commonroad_path_toolkit.libs/libopenblas-f650aae0.so.0
commonroad_path_toolkit.libs/libquadmath-96973f99.so.0
commonroad_path_toolkit/__init__.py
commonroad_path_toolkit/__init__.pyi
commonroad_path_toolkit/py.typed
commonroad_path_toolkit/commonroad_path_toolkit.cpython-311-x86_64-linux-gnu.so
commonroad_path_toolkit-0.0.1.dist-info/RECORD
