Metadata-Version: 2.3
Name: commonroad-path-toolkit
Version: 0.0.1
Classifier: Programming Language :: Rust
Classifier: Programming Language :: Python :: Implementation :: CPython
License-File: LICENSE
Summary: Useful functions for working with paths
Author-email: Kilian Northoff <kilian.northoff@tum.de>
License: BSD
Requires-Python: >=3.8, <3.13
